Metadata-Version: 2.1
Name: smiter
Version: 0.1.1
Summary: Library to create synthetic mzMLs file based on chemical formulas
Home-page: https://github.com/MKoesters/smiter
Author: Manuel Kösters
Author-email: manuel.koesters@dcb.unibe.ch
License: MIT license
Keywords: smiter
Platform: UNKNOWN
Classifier: Development Status :: 2 - Pre-Alpha
Classifier: Intended Audience :: Developers
Classifier: License :: OSI Approved :: MIT License
Classifier: Natural Language :: English
Classifier: Programming Language :: Python :: 3.7
Classifier: Programming Language :: Python :: 3.8
Classifier: Programming Language :: Python :: 3.9
Requires-Python: >=3.7
License-File: LICENSE
License-File: AUTHORS.rst
